<PAMDataset>
  <PAMRasterBand band="1">
    <Description>Band_1</Description>
    <Histograms>
      <HistItem>
        <HistMin>226.794921875</HistMin>
        <HistMax>255.3675994873047</HistMax>
        <BucketCount>256</BucketCount>
        <IncludeOutOfRange>1</IncludeOutOfRange>
        <Approximate>0</Approximate>
        <HistCounts>43|788|905|716|2106|1342|1486|1622|2647|2882|3170|4141|4475|4756|5327|6772|8529|9901|10914|14236|20464|14410|12727|9498|9602|11259|8521|9956|9595|10446|13036|14620|15198|22463|19849|16981|21993|23560|21348|25646|24928|21155|18603|18210|14821|16831|18548|19832|18846|15859|16797|15142|15226|11473|13001|14210|18360|22032|19568|16401|17310|18596|20053|14956|11309|9561|7021|5620|4521|4023|4058|3892|4024|4228|4299|3630|3613|3503|3167|3255|3391|3517|3488|3385|3323|3152|3226|3160|3303|3199|3114|1994|1508|1181|1089|1110|1136|1126|1176|1164|1242|1292|1284|1345|1439|1360|1355|1425|1353|1283|1206|1207|1226|1138|1149|1309|1382|1217|1288|1269|1220|1209|1165|1227|1157|1092|1085|1071|1024|999|965|941|950|925|959|965|1017|975|949|947|955|940|939|936|942|874|866|890|903|841|817|795|784|741|781|748|740|663|629|578|581|556|504|471|462|445|428|425|435|420|413|394|382|348|353|340|346|332|334|356|338|337|340|380|385|304|270|248|240|194|183|155|125|98|81|46|64|56|56|63|64|68|65|69|59|56|65|48|47|60|59|55|42|49|45|57|40|39|49|43|56|42|51|48|49|46|43|43|42|33|42|27|38|33|27|35|23|33|28|31|33|24|26|29|26|24|27|31|25|18|19|15|15|20|16|1</HistCounts>
      </HistItem>
    </Histograms>
    <Metadata>
      <MDI key="STATISTICS_MINIMUM">226.794921875</MDI>
      <MDI key="STATISTICS_MAXIMUM">255.3675994873</MDI>
      <MDI key="STATISTICS_MEAN">232.61716752166</MDI>
      <MDI key="STATISTICS_STDDEV">3.4992780942645</MDI>
      <MDI key="STATISTICS_MEDIAN">nan</MDI>
      <MDI key="STATISTICS_COUNT">1023613.000000</MDI>
      <MDI key="STATISTICS_SKIPFACTORX">1</MDI>
      <MDI key="STATISTICS_SKIPFACTORY">1</MDI>
      <MDI key="STATISTICS_EXCLUDEDVALUES"></MDI>
    </Metadata>
  </PAMRasterBand>
</PAMDataset>
